secretballot/__init__.py
secretballot/apps.py
secretballot/middleware.py
secretballot/models.py
secretballot/receivers.py
secretballot/settings.py
secretballot/utils.py
secretballot/views.py
secretballot/migrations/0001_initial.py
secretballot/migrations/0002_auto_20200328_0249.py
secretballot/migrations/__init__.py
secretballot/tests/__init__.py
secretballot/tests/conftest.py
secretballot/tests/models.py
secretballot/tests/settings.py
secretballot/tests/test_default.py
django_secretballot-2.0.0.dist-info/LICENSE
django_secretballot-2.0.0.dist-info/METADATA
django_secretballot-2.0.0.dist-info/WHEEL
django_secretballot-2.0.0.dist-info/top_level.txt
django_secretballot-2.0.0.dist-info/RECORD
