Metadata-Version: 2.1
Name: django-secretballot
Version: 2.0.0
Summary: Django anonymous voting application.
Home-page: https://github.com/bashu/django-secretballot/
Author: James Turk
Author-email: dev@jamesturk.net
Maintainer: Basil Shubin
Maintainer-email: basil.shubin@gmail.com
License: BSD License
Download-URL: https://github.com/bashu/django-secretballot/zipball/master
Platform: UNKNOWN
Classifier: Development Status :: 5 - Production/Stable
Classifier: Environment :: Web Environment
Classifier: Intended Audience :: Developers
Classifier: License :: OSI Approved :: BSD License
Classifier: Operating System :: OS Independent
Classifier: Programming Language :: Python
Classifier: Programming Language :: Python :: 3 :: Only
Classifier: Programming Language :: Python :: 3.6
Classifier: Programming Language :: Python :: 3.7
Classifier: Programming Language :: Python :: 3.8
Classifier: Programming Language :: Python :: 3.9
Classifier: Framework :: Django
Classifier: Framework :: Django :: 2.2
Classifier: Framework :: Django :: 3.0
Classifier: Framework :: Django :: 3.1
Classifier: Framework :: Django :: 3.2
Provides-Extra: develop
Provides-Extra: test
License-File: LICENSE
